{
  "param_name": "innodb_buffer_pool_size",
  "function_name": "ha_innobase::get_memory_buffer_size",
  "analysis": "<需要提供函数>\n除了现在给出的函数片段，尚未提供其他相关函数的具体实现，这可能影响分析的深入。建议提供函数名为：ha_innobase::get_memory_buffer_size 的完整实现，以便理解其机制。\n\n<思考过程>\n1. 参数通过控制关键函数对数据库性能的影响：\n    - innodb_buffer_pool_size 通过 [内存管理机制] 影响 ha_innobase::get_memory_buffer_size，进而产生[数据库性能影响]\n    - 机制：innodb_buffer_pool_size 控制InnoDB存储引擎在内存中的缓存大小。其值的变化会影响到内存分配和缓存命中率，从而可能间接影响 ha_innobase::get_memory_buffer_size 的行为，即影响到它能够获取的数据缓冲区大小。\n    - 数据库性能影响：如果 innodb_buffer_pool_size 设置太小，可能导致更多的磁盘I/O请求，因为缓存命中率下降。这会增加查询延迟，导致数据库性能降低。而设置合理的较大值可以提升查询响应速度和整体吞吐量，因为数据块更可能已经在内存中。\n\n<火焰图采样分析与调优方向>\n2. 基于 ha_innobase::get_memory_buffer_size执行状态和相关函数片段给出innodb_buffer_pool_size 优化建议：\n    - 如果涉及到[其他函数]，需要监控与内存缓冲区管理相关的函数，如：buf_page_get_gen、buf_page_create等，用于分析内存缓冲区分配与回收的具体影响。\n    - 如何根据 ha_innobase::get_memory_buffer_size和[其他函数]的火焰图采样率，推荐innodb_buffer_pool_size调整的方向：如果火焰图显示 ha_innobase::get_memory_buffer_size使用率频繁且其相关I/O操作占用较大时间，建议增加 innodb_buffer_pool_size 值，以减少数据库物理磁盘访问；若表现为缓存剩余量充足且未能充分利用，则考虑略微降低。依据火焰图中I/O相关函数与内存相关函数采样占比来调节此参数。",
  "code_snippets": "",
  "timestamp": "2025-07-27T22:49:39.817332"
}