{
  "param_name": "join_buffer_size",
  "function_name": "HashJoinIterator::BuildHashTable",
  "analysis": "<需要提供函数>\n没有需要给出其他函数的具体实现。\n\n<思考过程>\n1. 参数通过控制关键函数对数据库性能的影响：\n    - join_buffer_size通过影响内存分配机制影响HashJoinIterator::BuildHashTable，进而产生内存使用效率和处理速度上的性能影响。\n    - 机制：join_buffer_size决定了m_row_buffer的内存大小。如果m_row_buffer满了且不允许溢出到磁盘(m_allow_spill_to_disk为false)，则不能追加更多的行到行缓冲区，导致直接读取探测输入行(m_probe_input)。大的join_buffer_size可以存储更多行，减少m_row_buffer满时的探测输入读取频率，有效提高内存中数据处理的效率。\n    - 数据库性能影响：如果join_buffer_size过小，程序的m_row_buffer会频繁满溢并不得不进行次级处理，比如读探测行或者溢出到磁盘。这样不仅影响处理速度，还可能增加I/O操作。当设置为较大的值时，m_build_input的行可以完全存储在内存中，减少读操作和磁盘溢出成本，提高查询效率。\n\n<火焰图采样分析与调优方向>\n2. 基于HashJoinIterator::BuildHashTable执行状态和相关函数片段给出join_buffer_size优化建议：\n    - 如果涉及到[其他函数]，需要监控初始化和行缓冲区的相关操作，以确保优化是基于整个过程而做，比如监控InitRowBuffer, StoreRow,和WriteRowsToChunks函数的执行情况。\n    - 如何根据HashJoinIterator::BuildHashTable和[其他函数]的火焰图采样率，推荐join_buffer_size调整的方向（升高或降低）和依据：在火焰图中采样HashJoinIterator::BuildHashTable的频率较高且具体执行时间相对长时，可能是由于多次读取探测输入或频繁磁盘溢出操作（由于频繁的BUFFER_FULL）造成的。此时推荐升高join_buffer_size以减少这些操作的开销。当提高后看到火焰图中执行时间缩短，表示优化有效。如果没有显著变化，可能需要结合调整其他相关参数或分析其他位置上的瓶颈。",
  "code_snippets": "",
  "timestamp": "2025-07-28T04:22:13.472409"
}