{
  "param_name": "innodb_adaptive_flushing",
  "function_name": "Adaptive_flush::get_pct_for_lsn",
  "analysis": "<需要提供函数>\n除了现在给出的函数片段，当前分析不需要额外的具体函数实现。\n\n<思考过程>\n1. 参数通过控制关键函数对数据库性能的影响：\n    - innodb_adaptive_flushing 通过改变LSN (Log Sequence Number) 刷新的速率影响 Adaptive_flush::get_pct_for_lsn，进而产生对数据库写入性能的影响。\n    - 机制：innodb_adaptive_flushing 控制着是否启动自适应刷新的功能。当其启用时，自适应刷新会在LSN到达某一最小龄期（limit_for_dirty_page_age）后，根据特定比例（lsn_age_factor）调整刷新速率。这影响了日志中的脏页被刷新的频率，从而影响数据库的写入性能。参数的不同值（启用/禁用）会决定自适应刷新是否依赖LSN比较的结果来做出刷新决策。\n    - 数据库性能影响：启用后，随着日志序列号增长，自适应刷新机制可能加速脏页的刷新以减少IO写入压力，否则可能导致更高的IO等待。通过避免日志文件使用过满，自适应刷新有助于平衡内存和磁盘之间的脏页管理，提高写性能和稳定性。\n\n<火焰图采样分析与调优方向>\n2. 基于 Adaptive_flush::get_pct_for_lsn执行状态和相关函数片段给出innodb_adaptive_flushing 优化建议：\n    - 如果涉及到[其他函数]，需要监控log_files_capacity_get_limits，以保证其对limit_for_free_check和limit_for_dirty_page_age计算的合理性。\n    - 如何根据 Adaptive_flush::get_pct_for_lsn和log_files_capacity_get_limits的火焰图采样率，建议对innodb_adaptive_flushing进行调整：若Adaptive_flush::get_pct_for_lsn和log_files_capacity_get_limits在采样中出现的调用比例过高，并伴随着高IO等待时间，考虑升高innodb_adaptive_flushing以增加刷新效率，减少IO瓶颈；相反，若此调用比例低且未出现相关等待瓶颈，可以适当降低该参数值以节省系统资源。调优时，观察日志文件大小、IO性能和系统响应速度相结合，以优化整体性能。",
  "code_snippets": "",
  "timestamp": "2025-07-18T12:29:49.712043"
}