{
  "param_name": "innodb_io_capacity",
  "function_name": "std::chrono::_V2::steady_clock::now",
  "analysis": "关于参数 innodb_io_capacity 对 std::chrono::_V2::steady_clock::now 及其整体性能影响的分析报告\n\n---\n\n### 1. 参数对函数的直接影响：\n\n- **innodb_io_capacity** 通过影响 **InnoDB存储引擎内部的I/O调度与等待策略**，在某些情况下会间接影响 **代码中时间测量的频率和粒度**，包括调用 **std::chrono::_V2::steady_clock::now**。\n  \n- 影响方式：当 **innodb_io_capacity** 增加时，InnoDB会 presumed 改善 I/O 请求的排队和处理速度，从而减少数据库等待I/O完成的时间。这可能导致调用 **steady_clock::now** 的频率在高负载条件下略有变化，因为多线程调度中的I/O等待时间减短，代码中的等待/轮询逻辑可能提前结束或者频繁响应。\n\n- 性能影响：由于 **steady_clock::now** 多用于性能测量、延迟检测和时间戳同步，**innodb_io_capacity** 提高可能减少等待时间的延迟，导致 **调用频率的变化**，但其影响多是间接且微妙的。主要表现为内核I/O调度变化引起的时间片调整，可能使得时间测量的精度和稳定性有所不同。\n\n---\n\n### 2. 函数执行链分析\n\n- 当 **innodb_io_capacity** 增加时，InnoDB 内部管理模块的 I/O调度策略会调整，减少 I/O 阻塞等待时间。\n- 这影响到执行时间较长的数据库操作，特别是在多线程环境下，线程等待 I/O 完成的时间会缩短。\n- 反映到调用 **std::chrono::_V2::steady_clock::now** 的位置上，可能出现：\n  - 监控/统计代码中时间差的变化（比如操作延时统计），因为等待阶段变短；\n  - 控制逻辑中的等待条件提前满足，触发更频繁的时间测量；\n  - 由于I/O的响应变快，系统负载可能发生变化，影响**时间测量的稳定性和准确性**。\n\n- 综上，**innodb_io_capacity**的变化间接影响 **steady_clock::now** 调用的频率和结果的变化，从而影响整个性能监控和调度逻辑。\n\n---\n\n### 3. 关键性能点\n\n- **关键函数**：`std::chrono::_V2::steady_clock::now`\n  - 为什么它对性能影响最大？它是时间戳采集的基础，决定了基于时间的调度、统计和监控的准确性。\n- 影响最大的点在于：\n  - **等待时间的变化**：由于 I/O 调度改善，相关等待时间可能缩短，导致调用频率和累计耗时不同。\n  - **时间测量的微观偏差**：系统内部调度变化可能改变时间测量的粒度和一致性，影响性能分析的准确性。\n\n- 如何优化：\n  - 确保 `steady_clock` 的使用频率合理，避免在高频调用中引入过多性能开销。\n  - 根据工作负载动态调节 `innodb_io_capacity`，在高I/O压力或不同负载场景下调整参数，使得 `steady_clock::now` 调用的次数和时效性得到平衡。\n\n---\n\n### 4. 针对关键函数的参数优化建议\n\n- **调整方向**：\n  - 在高负载场景，**提高 `innodb_io_capacity`** 能减轻I/O等待，减少长时间阻塞，使得时间测量更为准确和一致，避免不必要的等待引起的时间偏差。\n  - 在低负载或延迟敏感场景，适当**降低 `innodb_io_capacity`**，减少后台I/O的调度压力，保证时间监控不受I/O激增的干扰。\n\n- **理论依据**：\n  - 提升 `innodb_io_capacity` ：减少等待时间，提升系统响应速度，从而使得调用 `steady_clock::now` 时的时间更接近真实的实际执行时间。\n  - 降低 `innodb_io_capacity` ：可能引起等待堆积，使得调用时间带有更多等待引入的延迟，从而影响性能分析的准确度。\n\n- **动态调整策略**：\n  - 根据监控统计数据显示的等待时间和调度延迟，在不同负载条件下动态调整 `innodb_io_capacity`。\n  - 在时间测量要求较高的场景（如性能基准测试、延时敏感的应用），建议将其设置为较高值。\n  - 在后台任务或非实时操作中，采取较低值，减少I/O调度对时间测量的影响。\n\n---\n\n### **总结**\n\n参数 **innodb_io_capacity**通过影响InnoDB内部I/O调度与等待策略，间接改变了**等待时间、调度频率**，从而影响了以时间为核心的函数 **std::chrono::_V2::steady_clock::now** 的调用频率和测量精度。提高该参数可以缩短等待时间，减少时间测量的偏差，优化性能监控的准确性；反之则可能增加等待引入的延迟与偏差。合理调节此参数，结合实际负载条件，是提升时间敏感应用性能和监控精度的关键。\n\n",
  "code_snippets": [],
  "timestamp": "2025-05-20T23:04:22.775288"
}