{
  "param_name": "innodb_read_ahead_threshold",
  "function_name": null,
  "analysis": "<需要提供函数>\n除了现在给出的函数片段，是否还需要给出其他函数的具体实现，如果有，则输出函数名\n无\n\n<思考过程>\n1. 参数通过控制关键函数对数据库性能的影响：\n    - innodb_read_ahead_threshold 通过预读机制影响数据库的读取行为，进而产生对磁盘I/O性能的影响\n    - 机制：innodb_read_ahead_threshold 值确定了读取请求触发预读操作的边界。较低的值可能导致更频繁的预读，而较高的值则需要更多确认读取模式后进行预读。\n    - 数据库性能影响：如果设置过低，可能造成不必要的预读，导致I/O瓶颈；如果设置过高，则可能未能有效利用预读，浪费潜在的读取效率。\n\n<火焰图采样分析与调优方向>\n2. 基于 None执行状态和相关函数片段给出innodb_read_ahead_threshold 优化建议：\n    - 如果涉及到[其他函数]，请指出除了监控None之外，是否还需要监控其他函数。\n    - 如何根据 None和[其他函数]的火焰图采样率，推荐innodb_read_ahead_threshold调整的方向（升高或降低）和依据\n    - 可能需要额外监控磁盘I/O相关函数，如果观察到频繁的读取瓶颈，可以建议降低 innodb_read_ahead_threshold 值，以减少不必要的预读；反之，如果观察到较长时间的等待却没有预读产生，建议升高该值，以增强预读效能。具体火焰图采样需要确定 I/O等待时间和预读操作频率，以指导合理的调优。",
  "code_snippets": "",
  "timestamp": "2025-06-04T03:27:16.352156"
}